pickpack/__init__.py
pickpack/anytree_utils.py
pickpack-1.0.1.dist-info/LICENSE
pickpack-1.0.1.dist-info/METADATA
pickpack-1.0.1.dist-info/WHEEL
pickpack-1.0.1.dist-info/RECORD
