Metadata-Version: 2.1
Name: pickpack
Version: 1.0.1
Summary: Based on wong2's pick, pickpack is a terminal GUI which allows you to pick one or more options from a tree structure
Home-page: https://github.com/anafvana/pickpack
License: MIT
Keywords: terminal,gui,pick,tree
Author: Ana
Author-email: anafvana@gmail.com
Requires-Python: >=3.9
Classifier: License :: OSI Approved :: MIT License
Classifier: Programming Language :: Python :: 3
Classifier: Programming Language :: Python :: 3.9
Classifier: Programming Language :: Python :: 3.10
Classifier: Programming Language :: Python :: 3.11
Requires-Dist: anytree (>=2.8,<3.0)
Requires-Dist: dataclasses (>=0.8,<0.9) ; python_version >= "3.6" and python_version < "3.7"
Requires-Dist: windows-curses (>=2.2.0,<3.0.0) ; sys_platform == "win32"
Project-URL: Repository, https://github.com/anafvana/pickpack
